{"BasePath":null,"Description":"sdt URLFoto","EntryPointMethods":null,"FullName":"sdtURLFoto","FullNameForInsert":null,"GrpcNameSpace":null,"HasGAM":false,"IsAPI":false,"IsBC":false,"IsDP":false,"IsGrpc":false,"IsSD":false,"IsSDT":true,"IsSvc":false,"Name":"sdtURLFoto","Parameters":null,"SDT":{"Attributes":[{"Alias":null,"CollectionItemName":null,"Decimals":0,"DefaultValue":null,"Description":"Link Exp5 Minutos","ExternalName":null,"FullName":null,"Inout":0,"IsBCSDT":false,"IsCollection":false,"IsFilterAtt":false,"IsKey":false,"IsNullable":false,"IsPathParameter":false,"IsReadOnly":false,"IsRequired":false,"IsWrapped":false,"JsonName":"","Length":2097152,"Name":"LinkExp5Minutos","SDTType":null,"Sign":0,"Type":8},{"Alias":null,"CollectionItemName":null,"Decimals":0,"DefaultValue":null,"Description":"fp_id","ExternalName":null,"FullName":null,"Inout":0,"IsBCSDT":false,"IsCollection":false,"IsFilterAtt":false,"IsKey":false,"IsNullable":false,"IsPathParameter":false,"IsReadOnly":false,"IsRequired":false,"IsWrapped":false,"JsonName":"","Length":4,"Name":"fp_id","SDTType":null,"Sign":0,"Type":4}],"CollectionItemName":null,"FullName":"sdtURLFoto","IsCollection":false,"IsSDTForInsert":false,"Name":"sdtURLFoto","ParentLevel":null,"SubLevels":null},"SDTForInsert":null,"isOData":false,"isOpenAPI":true,"isOpenAiPlugin":false,"isUseEnvironmentPropertyValueOpenAPI":false,"openAPIVersion":null,"openAiHumanDesc":null,"openAiModelDesc":null}